atomtools/__init__.py
atomtools/constants.py
atomtools/default_filetype.conf
atomtools/ext_types.py
atomtools/filetype.py
atomtools/fileutil.py
atomtools/geo.py
atomtools/methods.py
atomtools/name.py
atomtools/status.py
atomtools/string.py
atomtools/system.py
atomtools/unit.py
atomtools-1.9.4.dist-info/LICENSE
atomtools-1.9.4.dist-info/METADATA
atomtools-1.9.4.dist-info/WHEEL
atomtools-1.9.4.dist-info/entry_points.txt
atomtools-1.9.4.dist-info/top_level.txt
atomtools-1.9.4.dist-info/RECORD
